<?xml version='1.0' encoding='UTF-8'?>
<?artifactRepository version='1.1.0'?>
<repository name='E:\eclipse\dropins\MergeDoc' type='org.eclipse.equinox.p2.artifact.repository.simpleRepository' version='1.0.0'>
  <properties size='1'>
    <property name='p2.timestamp' value='1459906971251'/>
  </properties>
  <mappings size='3'>
    <rule filter='(&amp; (classifier=osgi.bundle))' output='${repoUrl}/plugins/${id}_${version}.jar'/>
    <rule filter='(&amp; (classifier=binary))' output='${repoUrl}/binary/${id}_${version}'/>
    <rule filter='(&amp; (classifier=org.eclipse.update.feature))' output='${repoUrl}/features/${id}_${version}.jar'/>
  </mappings>
  <artifacts size='3'>
    <artifact classifier='osgi.bundle' id='jp.sourceforge.mergedoc.pleiades' version='1.4.10'>
      <properties size='2'>
        <property name='artifact.size' value='4096'/>
        <property name='download.size' value='4096'/>
      </properties>
      <repositoryProperties size='3'>
        <property name='artifact.folder' value='true'/>
        <property name='artifact.reference' value='file:/E:/eclipse/dropins/MergeDoc/eclipse/plugins/jp.sourceforge.mergedoc.pleiades/'/>
        <property name='file.name' value='E:\eclipse\dropins\MergeDoc\eclipse\plugins\jp.sourceforge.mergedoc.pleiades'/>
      </repositoryProperties>
    </artifact>
    <artifact classifier='osgi.bundle' id='jp.sourceforge.mergedoc.PleiadesJavaPerspective' version='1.0.0'>
      <properties size='2'>
        <property name='artifact.size' value='4096'/>
        <property name='download.size' value='4096'/>
      </properties>
      <repositoryProperties size='3'>
        <property name='artifact.folder' value='true'/>
        <property name='artifact.reference' value='file:/E:/eclipse/dropins/MergeDoc/eclipse/plugins/jp.sourceforge.mergedoc.PleiadesJavaPerspective_1.0.0/'/>
        <property name='file.name' value='E:\eclipse\dropins\MergeDoc\eclipse\plugins\jp.sourceforge.mergedoc.PleiadesJavaPerspective_1.0.0'/>
      </repositoryProperties>
    </artifact>
    <artifact classifier='osgi.bundle' id='org.eclipse.jface.nl1' version='3.5.0.pleiades'>
      <properties size='2'>
        <property name='artifact.size' value='5570'/>
        <property name='download.size' value='5570'/>
      </properties>
      <repositoryProperties size='2'>
        <property name='artifact.reference' value='file:/E:/eclipse/dropins/MergeDoc/eclipse/plugins/org.eclipse.jface.nl1_3.5.0.pleiades.jar'/>
        <property name='file.name' value='E:\eclipse\dropins\MergeDoc\eclipse\plugins\org.eclipse.jface.nl1_3.5.0.pleiades.jar'/>
      </repositoryProperties>
    </artifact>
  </artifacts>
</repository>
